awthemes/__init__.py
awthemes/py.typed
awthemes/awthemes-10.4.0/LICENSE
awthemes/awthemes-10.4.0/README.txt
awthemes/awthemes-10.4.0/awarc.tcl
awthemes/awthemes-10.4.0/awblack.tcl
awthemes/awthemes-10.4.0/awbreeze.tcl
awthemes/awthemes-10.4.0/awbreezedark.tcl
awthemes/awthemes-10.4.0/awclearlooks.tcl
awthemes/awthemes-10.4.0/awdark.tcl
awthemes/awthemes-10.4.0/awlight.tcl
awthemes/awthemes-10.4.0/awtemplate.tcl
awthemes/awthemes-10.4.0/awthemes.n7
awthemes/awthemes-10.4.0/awthemes.tcl
awthemes/awthemes-10.4.0/awwinxpblue.tcl
awthemes/awthemes-10.4.0/colorutils.tcl
awthemes/awthemes-10.4.0/demoscaled.tcl
awthemes/awthemes-10.4.0/demoscaledb.tcl
awthemes/awthemes-10.4.0/demottk.tcl
awthemes/awthemes-10.4.0/pkgIndex.tcl
awthemes/awthemes-10.4.0/i/awthemes/README.txt
awthemes/awthemes-10.4.0/i/awthemes/arrow/chevron/arrow-down-d.svg
awthemes/awthemes-10.4.0/i/awthemes/arrow/chevron/arrow-down-n-base.svg
awthemes/awthemes-10.4.0/i/awthemes/arrow/chevron/arrow-down-n.svg
awthemes/awthemes-10.4.0/i/awthemes/arrow/chevron/arrow-down-sn.svg
awthemes/awthemes-10.4.0/i/awthemes/arrow/chevron/arrow-left-n.svg
awthemes/awthemes-10.4.0/i/awthemes/arrow/chevron/arrow-right-n.svg
awthemes/awthemes-10.4.0/i/awthemes/arrow/chevron/arrow-right-sn.svg
awthemes/awthemes-10.4.0/i/awthemes/arrow/chevron/arrow-up-d.svg
awthemes/awthemes-10.4.0/i/awthemes/arrow/chevron/arrow-up-n.svg
awthemes/awthemes-10.4.0/i/awthemes/arrow/open/arrow-down-n-base.svg
awthemes/awthemes-10.4.0/i/awthemes/arrow/open/arrow-down-n.svg
awthemes/awthemes-10.4.0/i/awthemes/arrow/open/arrow-down-sn.svg
awthemes/awthemes-10.4.0/i/awthemes/arrow/open/arrow-left-n.svg
awthemes/awthemes-10.4.0/i/awthemes/arrow/open/arrow-right-n.svg
awthemes/awthemes-10.4.0/i/awthemes/arrow/open/arrow-right-sn.svg
awthemes/awthemes-10.4.0/i/awthemes/arrow/open/arrow-up-n.svg
awthemes/awthemes-10.4.0/i/awthemes/arrow/solid/arrow-down-n-base.svg
awthemes/awthemes-10.4.0/i/awthemes/arrow/solid/arrow-down-n.svg
python_awthemes-0.2.1.dist-info/LICENSE
python_awthemes-0.2.1.dist-info/METADATA
python_awthemes-0.2.1.dist-info/WHEEL
python_awthemes-0.2.1.dist-info/top_level.txt
python_awthemes-0.2.1.dist-info/RECORD
