Metadata-Version: 2.1
Name: python-awthemes
Version: 0.2.1
Summary: A port of [tcl-awthemes] to Python ttk.
Author: undecV
Author-email: 22562116+undecV@users.noreply.github.com
License: Zlib
Classifier: Development Status :: 4 - Beta
Classifier: Intended Audience :: Developers
Classifier: License :: OSI Approved :: zlib/libpng License
Classifier: Programming Language :: Tcl
Classifier: Programming Language :: Python :: 3
Classifier: Programming Language :: Python :: 3.7
License-File: LICENSE
Requires-Dist: tksvg
